aivk/__about__.py
aivk/__init__.py
aivk/py.typed
aivk/api/__init__.py
aivk/api/setlogger.py
aivk/base/__init__.py
aivk/base/aivk.py
aivk/base/context.py
aivk/base/fastaivk.py
aivk/base/fs.py
aivk/base/loader.py
aivk/base/types.py
aivk/cli/__init__.py
aivk/cli/__main__.py
aivk/cli/amcp/__init__.py
aivk/cli/amcp/__main__.py
aivk/cli/dev/__init__.py
aivk/cli/dev/__main__.py
aivk/cli/install/__init__.py
aivk/cli/install/__main__.py
aivk/cli/run/__init__.py
aivk/cli/run/__main__.py
aivk/cli/shell/__init__.py
aivk/cli/shell/__main__.py
aivk/cli/uninstall/__init__.py
aivk/cli/uninstall/__main__.py
aivk-0.4.4.dist-info/METADATA
aivk-0.4.4.dist-info/WHEEL
aivk-0.4.4.dist-info/entry_points.txt
aivk-0.4.4.dist-info/licenses/LICENSE
aivk-0.4.4.dist-info/RECORD
