Metadata-Version: 2.4
Name: aivk
Version: 0.4.4
Summary: Aivk is ai Virtual Kernel
Author-email: LIghtJUNction <lightjunction.me@gmail.com>
License-File: LICENSE
Requires-Python: >=3.13
Requires-Dist: colorlog>=6.9.0
Requires-Dist: fastapi>=0.115.12
Requires-Dist: httpx>=0.28.1
Requires-Dist: mcp[cli]>=1.6.0
Requires-Dist: python-box>=7.3.2
Requires-Dist: python-dotenv>=1.1.0
Requires-Dist: requests>=2.32.3
Requires-Dist: toml>=0.10.2
Provides-Extra: cli
Requires-Dist: click>=8.1.8; extra == 'cli'
Provides-Extra: dev
Requires-Dist: pytest-cov>=6.1.1; extra == 'dev'
Requires-Dist: pytest-mock>=3.14.0; extra == 'dev'
Requires-Dist: pytest>=8.3.5; extra == 'dev'
Requires-Dist: pyupgrade>=3.19.1; extra == 'dev'
